bloch_sphere/__init__.py
bloch_sphere/animate_bloch.py
bloch_sphere/animate_bloch_compare.py
bloch_sphere-0.5.0.dist-info/LICENSE.txt
bloch_sphere-0.5.0.dist-info/METADATA
bloch_sphere-0.5.0.dist-info/WHEEL
bloch_sphere-0.5.0.dist-info/entry_points.txt
bloch_sphere-0.5.0.dist-info/top_level.txt
bloch_sphere-0.5.0.dist-info/RECORD
