Metadata-Version: 2.1
Name: bloch-sphere
Version: 0.5.0
Summary: Visualization tools for the qubit Bloch sphere
Home-page: https://github.com/cduck/bloch_sphere
Download-URL: https://github.com/cduck/bloch_sphere/archive/0.5.0.tar.gz
Author: Casey Duckering
License: UNKNOWN
Keywords: quantum computing,qubit,jupyter
Platform: UNKNOWN
Classifier: License :: OSI Approved :: MIT License
Classifier: Development Status :: 3 - Alpha
Classifier: Programming Language :: Python :: 3
Classifier: Framework :: IPython
Classifier: Framework :: Jupyter
License-File: LICENSE.txt
Requires-Dist: numpy
Requires-Dist: drawSvg (~=2.0)
Requires-Dist: hyperbolic (~=2.0)
Requires-Dist: latextools (~=0.5.0)
